LICENSE
MANIFEST.in
README.md
VERSION
requirements.txt
setup.py
countergentorch/__init__.py
countergentorch.egg-info/PKG-INFO
countergentorch.egg-info/SOURCES.txt
countergentorch.egg-info/dependency_links.txt
countergentorch.egg-info/requires.txt
countergentorch.egg-info/top_level.txt
countergentorch/editing/__init__.py
countergentorch/editing/activation_ds.py
countergentorch/editing/activation_utils.py
countergentorch/editing/direction_algos.py
countergentorch/editing/edition.py
countergentorch/editing/models.py
countergentorch/evaluation/__init__.py
countergentorch/evaluation/classification_models.py
countergentorch/evaluation/generative_models.py
countergentorch/tools/__init__.py
countergentorch/tools/math_utils.py
countergentorch/tools/utils.py